distilnlp/__init__.py
distilnlp/tests/__init__.py
distilnlp/tests/test_normalize.py
distilnlp/text_normalize/__init__.py
distilnlp/text_normalize/emoji.py
distilnlp/text_normalize/text_normalize.py
distilNLP-0.0.6.dist-info/LICENSE
distilNLP-0.0.6.dist-info/METADATA
distilNLP-0.0.6.dist-info/WHEEL
distilNLP-0.0.6.dist-info/top_level.txt
distilNLP-0.0.6.dist-info/RECORD
