Metadata-Version: 2.1
Name: distilNLP
Version: 0.0.6
Summary: distilNLP is a low-dependency, GPU-free natural language processing toolkit.
Author-email: wencan <i@wencan.org>
License: BSD 3-Clause License
Project-URL: Homepage, https://github.com/wencan/distilNLP
Project-URL: Issues, https://github.com/wencan/distilNLP/issues
Classifier: Programming Language :: Python :: 3
Classifier: Operating System :: OS Independent
Requires-Python: >=3.8
License-File: LICENSE
